{ "columns":1,
 "image":"tiles\/greenWall.png",
 "imageheight":16,
 "imagewidth":32,
 "margin":0,
 "name":"greenWall",
 "spacing":0,
 "tilecount":1,
 "tileheight":16,
 "tiles":
    {
     "0":
        {
         "objectgroup":
            {
             "draworder":"index",
             "name":"",
             "objects":[
                    {
                     "height":16,
                     "id":2,
                     "name":"",
                     "rotation":0,
                     "type":"",
                     "visible":true,
                     "width":32,
                     "x":0,
                     "y":0
                    }],
             "opacity":1,
             "type":"objectgroup",
             "visible":true,
             "x":0,
             "y":0
            }
        }
    },
 "tilewidth":32,
 "type":"tileset"
}